{
"meta":{"test_sets":[],"test_metrics":[],"learn_metrics":[{"best_value":"Min","name":"Logloss"}],"launch_mode":"Train","parameters":"","iteration_count":240,"learn_sets":["learn"],"name":"experiment"},
"iterations":[
{"learn":[0.6755612077],"iteration":0,"passed_time":0.001058487878,"remaining_time":0.2529786028},
{"learn":[0.6613375306],"iteration":1,"passed_time":0.001901724903,"remaining_time":0.2263052635},
{"learn":[0.6470508883],"iteration":2,"passed_time":0.002700751381,"remaining_time":0.2133593591},
{"learn":[0.6327290016],"iteration":3,"passed_time":0.00351610129,"remaining_time":0.2074499761},
{"learn":[0.6204471832],"iteration":4,"passed_time":0.004305277594,"remaining_time":0.2023480469},
{"learn":[0.6088903539],"iteration":5,"passed_time":0.005128233081,"remaining_time":0.2000010902},
{"learn":[0.5972634012],"iteration":6,"passed_time":0.005980638884,"remaining_time":0.1990698371},
{"learn":[0.5871095224],"iteration":7,"passed_time":0.006775587009,"remaining_time":0.1964920233},
{"learn":[0.5776525072],"iteration":8,"passed_time":0.007584303333,"remaining_time":0.1946637855},
{"learn":[0.5689139267],"iteration":9,"passed_time":0.008371505593,"remaining_time":0.1925446286},
{"learn":[0.5604617632],"iteration":10,"passed_time":0.009161643867,"remaining_time":0.1907287678},
{"learn":[0.5522125722],"iteration":11,"passed_time":0.009970620725,"remaining_time":0.1894417938},
{"learn":[0.544356913],"iteration":12,"passed_time":0.01074327319,"remaining_time":0.1875940779},
{"learn":[0.5373150781],"iteration":13,"passed_time":0.01155347255,"remaining_time":0.1865060568},
{"learn":[0.5314449964],"iteration":14,"passed_time":0.0123444325,"remaining_time":0.1851664876},
{"learn":[0.5261187162],"iteration":15,"passed_time":0.01321273086,"remaining_time":0.184978232},
{"learn":[0.5206131736],"iteration":16,"passed_time":0.01409964734,"remaining_time":0.1849541975},
{"learn":[0.5148228066],"iteration":17,"passed_time":0.01492886565,"remaining_time":0.1841226764},
{"learn":[0.5095143283],"iteration":18,"passed_time":0.0156997545,"remaining_time":0.182612934},
{"learn":[0.5056115355],"iteration":19,"passed_time":0.01651315041,"remaining_time":0.1816446545},
{"learn":[0.5017403531],"iteration":20,"passed_time":0.01729632442,"remaining_time":0.1803759547},
{"learn":[0.4974228909],"iteration":21,"passed_time":0.01808391748,"remaining_time":0.1791951823},
{"learn":[0.4944766542],"iteration":22,"passed_time":0.01884948543,"remaining_time":0.1778407974},
{"learn":[0.4902039031],"iteration":23,"passed_time":0.01968470604,"remaining_time":0.1771623544},
{"learn":[0.4874804966],"iteration":24,"passed_time":0.02048735995,"remaining_time":0.1761912956},
{"learn":[0.4850707682],"iteration":25,"passed_time":0.02128568499,"remaining_time":0.1751975611},
{"learn":[0.482236733],"iteration":26,"passed_time":0.02206847822,"remaining_time":0.1740957726},
{"learn":[0.4797219221],"iteration":27,"passed_time":0.02282159066,"remaining_time":0.1727920436},
{"learn":[0.4766463078],"iteration":28,"passed_time":0.02360405322,"remaining_time":0.1717398355},
{"learn":[0.4735961633],"iteration":29,"passed_time":0.02441810046,"remaining_time":0.1709267032},
{"learn":[0.4704025455],"iteration":30,"passed_time":0.02520202601,"remaining_time":0.1699104334},
{"learn":[0.467715245],"iteration":31,"passed_time":0.02600069175,"remaining_time":0.1690044963},
{"learn":[0.4653757915],"iteration":32,"passed_time":0.02685929023,"remaining_time":0.1684810024},
{"learn":[0.46344073],"iteration":33,"passed_time":0.02766694438,"remaining_time":0.1676291336},
{"learn":[0.4613315078],"iteration":34,"passed_time":0.02843192112,"remaining_time":0.1665298237},
{"learn":[0.4604783166],"iteration":35,"passed_time":0.02932927899,"remaining_time":0.1661992476},
{"learn":[0.4591029249],"iteration":36,"passed_time":0.03027927548,"remaining_time":0.1661268357},
{"learn":[0.4574473997],"iteration":37,"passed_time":0.03114185211,"remaining_time":0.1655435297},
{"learn":[0.4564378757],"iteration":38,"passed_time":0.03195400548,"remaining_time":0.1646860282},
{"learn":[0.4549368614],"iteration":39,"passed_time":0.03275946513,"remaining_time":0.1637973257},
{"learn":[0.453011884],"iteration":40,"passed_time":0.03358635868,"remaining_time":0.1630167165},
{"learn":[0.4516326882],"iteration":41,"passed_time":0.03439293061,"remaining_time":0.1621381015},
{"learn":[0.4505702312],"iteration":42,"passed_time":0.03519944242,"remaining_time":0.1612625618},
{"learn":[0.448897424],"iteration":43,"passed_time":0.03601503282,"remaining_time":0.1604306008},
{"learn":[0.4481119682],"iteration":44,"passed_time":0.03700011035,"remaining_time":0.1603338115},
{"learn":[0.4464835838],"iteration":45,"passed_time":0.0378059107,"remaining_time":0.1594423191},
{"learn":[0.4456404528],"iteration":46,"passed_time":0.0386130538,"remaining_time":0.1585599869},
{"learn":[0.4441506645],"iteration":47,"passed_time":0.03943992732,"remaining_time":0.1577597093},
{"learn":[0.443179337],"iteration":48,"passed_time":0.04026364436,"remaining_time":0.1569460423},
{"learn":[0.4423671758],"iteration":49,"passed_time":0.04109697109,"remaining_time":0.1561684901},
{"learn":[0.4417151145],"iteration":50,"passed_time":0.04189038607,"remaining_time":0.1552408425},
{"learn":[0.4409011307],"iteration":51,"passed_time":0.04309950164,"remaining_time":0.1558212752},
{"learn":[0.4400824632],"iteration":52,"passed_time":0.04457482323,"remaining_time":0.1572734329},
{"learn":[0.4392911708],"iteration":53,"passed_time":0.04542060547,"remaining_time":0.1564487522},
{"learn":[0.4386960995],"iteration":54,"passed_time":0.04640877013,"remaining_time":0.1561022268},
{"learn":[0.4376817467],"iteration":55,"passed_time":0.04734208164,"remaining_time":0.1555525539},
{"learn":[0.4369730985],"iteration":56,"passed_time":0.04836090747,"remaining_time":0.1552639661},
{"learn":[0.43590531],"iteration":57,"passed_time":0.04914506349,"remaining_time":0.1542138199},
{"learn":[0.435264746],"iteration":58,"passed_time":0.04994102369,"remaining_time":0.1532089032},
{"learn":[0.4343396475],"iteration":59,"passed_time":0.05072763474,"remaining_time":0.1521829042},
{"learn":[0.4341162291],"iteration":60,"passed_time":0.05180996144,"remaining_time":0.1520325098},
{"learn":[0.4338325486],"iteration":61,"passed_time":0.05246438175,"remaining_time":0.1506235476},
{"learn":[0.4334455148],"iteration":62,"passed_time":0.0532455717,"remaining_time":0.1495947014},
{"learn":[0.4327481972],"iteration":63,"passed_time":0.05401955689,"remaining_time":0.1485537815},
{"learn":[0.4313709985],"iteration":64,"passed_time":0.05482282205,"remaining_time":0.1475999055},
{"learn":[0.4308223373],"iteration":65,"passed_time":0.0556121687,"remaining_time":0.1466138993},
{"learn":[0.4299423163],"iteration":66,"passed_time":0.05639763741,"remaining_time":0.1456237503},
{"learn":[0.4290346067],"iteration":67,"passed_time":0.05717817603,"remaining_time":0.1446271511},
{"learn":[0.4284849114],"iteration":68,"passed_time":0.05796867504,"remaining_time":0.143661499},
{"learn":[0.4279548443],"iteration":69,"passed_time":0.05914462349,"remaining_time":0.1436369428},
{"learn":[0.4272784674],"iteration":70,"passed_time":0.06004807384,"remaining_time":0.1429313307},
{"learn":[0.4266119184],"iteration":71,"passed_time":0.06093497028,"remaining_time":0.1421815973},
{"learn":[0.4260475549],"iteration":72,"passed_time":0.06182936207,"remaining_time":0.141445253},
{"learn":[0.4256062587],"iteration":73,"passed_time":0.06268108648,"remaining_time":0.1406089237},
{"learn":[0.4252946674],"iteration":74,"passed_time":0.06356157981,"remaining_time":0.1398354756},
{"learn":[0.4243400937],"iteration":75,"passed_time":0.064437123,"remaining_time":0.1390485286},
{"learn":[0.423972397],"iteration":76,"passed_time":0.06526733335,"remaining_time":0.138163316},
{"learn":[0.4233585042],"iteration":77,"passed_time":0.06613273577,"remaining_time":0.1373526051},
{"learn":[0.422997233],"iteration":78,"passed_time":0.06708416519,"remaining_time":0.1367158303},
{"learn":[0.4226345956],"iteration":79,"passed_time":0.06784531409,"remaining_time":0.1356906282},
{"learn":[0.4223163632],"iteration":80,"passed_time":0.06858206302,"remaining_time":0.1346240496},
{"learn":[0.4218775969],"iteration":81,"passed_time":0.06936651966,"remaining_time":0.1336574403},
{"learn":[0.4215556319],"iteration":82,"passed_time":0.07017413372,"remaining_time":0.132739024},
{"learn":[0.4209393227],"iteration":83,"passed_time":0.07097822057,"remaining_time":0.1318166953},
{"learn":[0.4206291923],"iteration":84,"passed_time":0.07174916954,"remaining_time":0.1308367209},
{"learn":[0.4200816435],"iteration":85,"passed_time":0.07256381801,"remaining_time":0.1299398602},
{"learn":[0.4197818748],"iteration":86,"passed_time":0.07335307448,"remaining_time":0.1290002344},
{"learn":[0.4189717407],"iteration":87,"passed_time":0.07448857495,"remaining_time":0.128662084},
{"learn":[0.4186801952],"iteration":88,"passed_time":0.07531889552,"remaining_time":0.1277882385},
{"learn":[0.4183085006],"iteration":89,"passed_time":0.07621476033,"remaining_time":0.1270246006},
{"learn":[0.4177858541],"iteration":90,"passed_time":0.07700872645,"remaining_time":0.1260912114},
{"learn":[0.4175666467],"iteration":91,"passed_time":0.07782854551,"remaining_time":0.1252024428},
{"learn":[0.4173329543],"iteration":92,"passed_time":0.07860861316,"remaining_time":0.124252324},
{"learn":[0.4170323136],"iteration":93,"passed_time":0.07936674588,"remaining_time":0.1232717542},
{"learn":[0.4168311604],"iteration":94,"passed_time":0.08016424924,"remaining_time":0.1223559594},
{"learn":[0.41646249],"iteration":95,"passed_time":0.08097993985,"remaining_time":0.1214699098},
{"learn":[0.4159900409],"iteration":96,"passed_time":0.08207103884,"remaining_time":0.1209913253},
{"learn":[0.4154604616],"iteration":97,"passed_time":0.08291824399,"remaining_time":0.1201468433},
{"learn":[0.4151788764],"iteration":98,"passed_time":0.08375264292,"remaining_time":0.1192840672},
{"learn":[0.4149771932],"iteration":99,"passed_time":0.08459070935,"remaining_time":0.1184269931},
{"learn":[0.4146017],"iteration":100,"passed_time":0.08545697354,"remaining_time":0.1176091022},
{"learn":[0.4141486611],"iteration":101,"passed_time":0.08633186539,"remaining_time":0.1168019355},
{"learn":[0.4140280714],"iteration":102,"passed_time":0.08716178514,"remaining_time":0.1159336366},
{"learn":[0.4138800083],"iteration":103,"passed_time":0.08801547358,"remaining_time":0.1150971578},
{"learn":[0.4136677659],"iteration":104,"passed_time":0.08887221827,"remaining_time":0.1142642806},
{"learn":[0.4132906967],"iteration":105,"passed_time":0.08998707213,"remaining_time":0.1137572421},
{"learn":[0.4132235096],"iteration":106,"passed_time":0.0909391824,"remaining_time":0.1130365538},
{"learn":[0.4128095933],"iteration":107,"passed_time":0.09179180866,"remaining_time":0.1121899884},
{"learn":[0.4126900998],"iteration":108,"passed_time":0.09261256965,"remaining_time":0.1113050149},
{"learn":[0.4124915079],"iteration":109,"passed_time":0.09347977577,"remaining_time":0.1104760986},
{"learn":[0.4120771023],"iteration":110,"passed_time":0.09430443474,"remaining_time":0.1095970458},
{"learn":[0.4116767672],"iteration":111,"passed_time":0.09517313392,"remaining_time":0.1087692959},
{"learn":[0.4115745758],"iteration":112,"passed_time":0.09600174098,"remaining_time":0.107895762},
{"learn":[0.4111945556],"iteration":113,"passed_time":0.09701633896,"remaining_time":0.1072285852},
{"learn":[0.4109510061],"iteration":114,"passed_time":0.0978794066,"remaining_time":0.1063906594},
{"learn":[0.4107460178],"iteration":115,"passed_time":0.09871634072,"remaining_time":0.1055243642},
{"learn":[0.4101713171],"iteration":116,"passed_time":0.09955691229,"remaining_time":0.104662395},
{"learn":[0.4098619062],"iteration":117,"passed_time":0.1004056105,"remaining_time":0.1038091905},
{"learn":[0.409694942],"iteration":118,"passed_time":0.1012563529,"remaining_time":0.1029581403},
{"learn":[0.4095668028],"iteration":119,"passed_time":0.1021148011,"remaining_time":0.1021148011},
{"learn":[0.409173957],"iteration":120,"passed_time":0.1029992425,"remaining_time":0.1012967757},
{"learn":[0.4087887754],"iteration":121,"passed_time":0.103867631,"remaining_time":0.1004621349},
{"learn":[0.4085896765],"iteration":122,"passed_time":0.1048472474,"remaining_time":0.0997327475},
{"learn":[0.4082663534],"iteration":123,"passed_time":0.1057460682,"remaining_time":0.09892374125},
{"learn":[0.408055157],"iteration":124,"passed_time":0.1067831322,"remaining_time":0.09824048165},
{"learn":[0.4077147284],"iteration":125,"passed_time":0.1076645374,"remaining_time":0.09741077196},
{"learn":[0.4076983004],"iteration":126,"passed_time":0.1083871073,"remaining_time":0.09643892226},
{"learn":[0.4076281157],"iteration":127,"passed_time":0.1091532464,"remaining_time":0.09550909063},
{"learn":[0.4074623563],"iteration":128,"passed_time":0.1099628337,"remaining_time":0.09461918252},
{"learn":[0.4069548686],"iteration":129,"passed_time":0.1107566996,"remaining_time":0.09371720739},
{"learn":[0.4066719301],"iteration":130,"passed_time":0.1116589876,"remaining_time":0.09290709656},
{"learn":[0.4065043067],"iteration":131,"passed_time":0.1125103212,"remaining_time":0.09205389918},
{"learn":[0.4063432745],"iteration":132,"passed_time":0.1133033955,"remaining_time":0.09115385954},
{"learn":[0.4061702713],"iteration":133,"passed_time":0.1141484611,"remaining_time":0.09029654389},
{"learn":[0.4055714659],"iteration":134,"passed_time":0.1149996845,"remaining_time":0.08944419907},
{"learn":[0.4055385768],"iteration":135,"passed_time":0.1158063667,"remaining_time":0.08855780981},
{"learn":[0.405103299],"iteration":136,"passed_time":0.1166270976,"remaining_time":0.08768314638},
{"learn":[0.4049368346],"iteration":137,"passed_time":0.1174625186,"remaining_time":0.08682012246},
{"learn":[0.4047555808],"iteration":138,"passed_time":0.1183358373,"remaining_time":0.08598503283},
{"learn":[0.4045915749],"iteration":139,"passed_time":0.1197561012,"remaining_time":0.0855400723},
{"learn":[0.4044853324],"iteration":140,"passed_time":0.120963925,"remaining_time":0.08493211752},
{"learn":[0.4040883277],"iteration":141,"passed_time":0.1219597653,"remaining_time":0.08416941551},
{"learn":[0.4038192341],"iteration":142,"passed_time":0.1227778108,"remaining_time":0.08328285066},
{"learn":[0.4034821486],"iteration":143,"passed_time":0.1236438336,"remaining_time":0.08242922243},
{"learn":[0.4032047236],"iteration":144,"passed_time":0.1245403698,"remaining_time":0.08159541472},
{"learn":[0.4031187963],"iteration":145,"passed_time":0.1253567218,"remaining_time":0.08070912225},
{"learn":[0.4030725221],"iteration":146,"passed_time":0.126128292,"remaining_time":0.07979545007},
{"learn":[0.4029049928],"iteration":147,"passed_time":0.1272913045,"remaining_time":0.07912702714},
{"learn":[0.4027131749],"iteration":148,"passed_time":0.1280660312,"remaining_time":0.07821482445},
{"learn":[0.4026652995],"iteration":149,"passed_time":0.128828062,"remaining_time":0.07729683717},
{"learn":[0.4022970419],"iteration":150,"passed_time":0.1296237316,"remaining_time":0.07640074244},
{"learn":[0.4020869533],"iteration":151,"passed_time":0.1303775755,"remaining_time":0.07548175423},
{"learn":[0.4018475095],"iteration":152,"passed_time":0.1311367604,"remaining_time":0.07456796178},
{"learn":[0.4016612681],"iteration":153,"passed_time":0.1319066772,"remaining_time":0.0736621704},
{"learn":[0.4011843704],"iteration":154,"passed_time":0.1331638715,"remaining_time":0.07302534891},
{"learn":[0.4010545808],"iteration":155,"passed_time":0.1339757243,"remaining_time":0.07214077462},
{"learn":[0.4007692885],"iteration":156,"passed_time":0.1348072674,"remaining_time":0.07126753625},
{"learn":[0.4003783874],"iteration":157,"passed_time":0.1356059231,"remaining_time":0.07037775755},
{"learn":[0.4003441138],"iteration":158,"passed_time":0.13639539,"remaining_time":0.06948444395},
{"learn":[0.4000763251],"iteration":159,"passed_time":0.1374570944,"remaining_time":0.06872854722},
{"learn":[0.3999569527],"iteration":160,"passed_time":0.1384119801,"remaining_time":0.06791643746},
{"learn":[0.3997245142],"iteration":161,"passed_time":0.1393757139,"remaining_time":0.06710682523},
{"learn":[0.3994800932],"iteration":162,"passed_time":0.1403826963,"remaining_time":0.06631575226},
{"learn":[0.3993889504],"iteration":163,"passed_time":0.1412786313,"remaining_time":0.06547058523},
{"learn":[0.399155062],"iteration":164,"passed_time":0.1422380964,"remaining_time":0.06465368017},
{"learn":[0.3990547771],"iteration":165,"passed_time":0.1430418625,"remaining_time":0.06376564957},
{"learn":[0.3988474247],"iteration":166,"passed_time":0.1438380532,"remaining_time":0.06287531668},
{"learn":[0.3986613661],"iteration":167,"passed_time":0.1446576318,"remaining_time":0.06199612791},
{"learn":[0.3985201007],"iteration":168,"passed_time":0.1454741441,"remaining_time":0.06111635639},
{"learn":[0.398501108],"iteration":169,"passed_time":0.1462497927,"remaining_time":0.06022050287},
{"learn":[0.3981828368],"iteration":170,"passed_time":0.147045813,"remaining_time":0.05933427542},
{"learn":[0.3980499182],"iteration":171,"passed_time":0.1478224135,"remaining_time":0.05844141931},
{"learn":[0.3976277271],"iteration":172,"passed_time":0.1486105076,"remaining_time":0.05755435845},
{"learn":[0.39741461],"iteration":173,"passed_time":0.1497494156,"remaining_time":0.05680150248},
{"learn":[0.3971066886],"iteration":174,"passed_time":0.1505473198,"remaining_time":0.05591757593},
{"learn":[0.3967520326],"iteration":175,"passed_time":0.151331556,"remaining_time":0.05502965672},
{"learn":[0.3965522115],"iteration":176,"passed_time":0.1521084271,"remaining_time":0.05414028761},
{"learn":[0.3964892304],"iteration":177,"passed_time":0.1529687543,"remaining_time":0.05328125148},
{"learn":[0.3957445298],"iteration":178,"passed_time":0.1537575698,"remaining_time":0.05239783106},
{"learn":[0.3953248329],"iteration":179,"passed_time":0.1545252822,"remaining_time":0.05150842739},
{"learn":[0.3952622114],"iteration":180,"passed_time":0.1553793709,"remaining_time":0.05064852421},
{"learn":[0.3950826386],"iteration":181,"passed_time":0.1562156737,"remaining_time":0.04978301689},
{"learn":[0.3950044204],"iteration":182,"passed_time":0.1571513701,"remaining_time":0.0489487874},
{"learn":[0.3946785015],"iteration":183,"passed_time":0.1579512082,"remaining_time":0.04807210685},
{"learn":[0.3943804361],"iteration":184,"passed_time":0.1587738731,"remaining_time":0.04720304336},
{"learn":[0.3940257003],"iteration":185,"passed_time":0.1595812567,"remaining_time":0.04633004227},
{"learn":[0.3937865054],"iteration":186,"passed_time":0.1603651221,"remaining_time":0.0454510774},
{"learn":[0.3936093036],"iteration":187,"passed_time":0.1611591083,"remaining_time":0.04457592357},
{"learn":[0.3934583297],"iteration":188,"passed_time":0.1619422923,"remaining_time":0.0436987138},
{"learn":[0.3931368203],"iteration":189,"passed_time":0.1627325108,"remaining_time":0.04282434494},
{"learn":[0.3930155581],"iteration":190,"passed_time":0.1635127087,"remaining_time":0.04194828652},
{"learn":[0.3928185862],"iteration":191,"passed_time":0.1644153574,"remaining_time":0.04110383935},
{"learn":[0.392778095],"iteration":192,"passed_time":0.1651736605,"remaining_time":0.04022363752},
{"learn":[0.3926929141],"iteration":193,"passed_time":0.165940992,"remaining_time":0.03934683316},
{"learn":[0.3924539904],"iteration":194,"passed_time":0.1667071612,"remaining_time":0.03847088335},
{"learn":[0.3920396464],"iteration":195,"passed_time":0.1674787815,"remaining_time":0.03759727749},
{"learn":[0.3917702297],"iteration":196,"passed_time":0.1686146327,"remaining_time":0.03680420918},
{"learn":[0.3916446075],"iteration":197,"passed_time":0.1694771392,"remaining_time":0.0359496962},
{"learn":[0.3912356873],"iteration":198,"passed_time":0.1704353016,"remaining_time":0.03511481089},
{"learn":[0.3911003796],"iteration":199,"passed_time":0.1712975175,"remaining_time":0.03425950351},
{"learn":[0.3908796015],"iteration":200,"passed_time":0.1724540814,"remaining_time":0.03346123968},
{"learn":[0.3907434668],"iteration":201,"passed_time":0.1733330115,"remaining_time":0.03260720019},
{"learn":[0.3906019215],"iteration":202,"passed_time":0.1742008489,"remaining_time":0.03175089365},
{"learn":[0.3904494732],"iteration":203,"passed_time":0.1753096306,"remaining_time":0.03093699364},
{"learn":[0.3902780604],"iteration":204,"passed_time":0.1762045335,"remaining_time":0.03008370084},
{"learn":[0.3902481021],"iteration":205,"passed_time":0.1770606369,"remaining_time":0.02922360026},
{"learn":[0.3900526015],"iteration":206,"passed_time":0.177935178,"remaining_time":0.02836647765},
{"learn":[0.3897965801],"iteration":207,"passed_time":0.1788327162,"remaining_time":0.02751272557},
{"learn":[0.3897547234],"iteration":208,"passed_time":0.1796951426,"remaining_time":0.0266533465},
{"learn":[0.389629927],"iteration":209,"passed_time":0.1805697338,"remaining_time":0.02579567626},
{"learn":[0.3895274529],"iteration":210,"passed_time":0.1814168488,"remaining_time":0.02493406926},
{"learn":[0.3890835335],"iteration":211,"passed_time":0.1822941756,"remaining_time":0.02407658923},
{"learn":[0.3885646668],"iteration":212,"passed_time":0.1831818637,"remaining_time":0.02322023624},
{"learn":[0.3884835639],"iteration":213,"passed_time":0.1841968817,"remaining_time":0.0223790604},
{"learn":[0.3883290889],"iteration":214,"passed_time":0.1850483456,"remaining_time":0.02151724949},
{"learn":[0.3881852168],"iteration":215,"passed_time":0.1858947992,"remaining_time":0.02065497769},
{"learn":[0.3879525911],"iteration":216,"passed_time":0.186702303,"remaining_time":0.01978872336},
{"learn":[0.3878425205],"iteration":217,"passed_time":0.1875500493,"remaining_time":0.0189270692},
{"learn":[0.3878237118],"iteration":218,"passed_time":0.1883659403,"remaining_time":0.01806248743},
{"learn":[0.3875738299],"iteration":219,"passed_time":0.1892818362,"remaining_time":0.01720743965},
{"learn":[0.3871853524],"iteration":220,"passed_time":0.1901683218,"remaining_time":0.01634931273},
{"learn":[0.3870961194],"iteration":221,"passed_time":0.191033143,"remaining_time":0.01548917376},
{"learn":[0.3869059317],"iteration":222,"passed_time":0.1918995575,"remaining_time":0.01462911425},
{"learn":[0.3868672494],"iteration":223,"passed_time":0.1927666033,"remaining_time":0.01376904309},
{"learn":[0.3867523827],"iteration":224,"passed_time":0.1936345309,"remaining_time":0.01290896872},
{"learn":[0.3862338325],"iteration":225,"passed_time":0.1946211716,"remaining_time":0.01205617877},
{"learn":[0.3859544535],"iteration":226,"passed_time":0.1955784422,"remaining_time":0.01120052753},
{"learn":[0.3859259906],"iteration":227,"passed_time":0.1964404376,"remaining_time":0.0103389704},
{"learn":[0.3857725105],"iteration":228,"passed_time":0.1973105497,"remaining_time":0.00947779933},
{"learn":[0.3854718019],"iteration":229,"passed_time":0.1981747196,"remaining_time":0.008616292156},
{"learn":[0.3853141098],"iteration":230,"passed_time":0.1990494712,"remaining_time":0.007755174201},
{"learn":[0.3852951162],"iteration":231,"passed_time":0.1998720058,"remaining_time":0.00689213813},
{"learn":[0.3852673586],"iteration":232,"passed_time":0.2007332597,"remaining_time":0.006030612952},
{"learn":[0.385260779],"iteration":233,"passed_time":0.2015628889,"remaining_time":0.005168279201},
{"learn":[0.3852535107],"iteration":234,"passed_time":0.2025520147,"remaining_time":0.004309617333},
{"learn":[0.385222258],"iteration":235,"passed_time":0.2043719921,"remaining_time":0.00346393207},
{"learn":[0.3848939056],"iteration":236,"passed_time":0.2052584377,"remaining_time":0.002598208072},
{"learn":[0.3848190328],"iteration":237,"passed_time":0.2061380793,"remaining_time":0.001732252767},
{"learn":[0.3847413038],"iteration":238,"passed_time":0.2069891724,"remaining_time":0.0008660634827},
{"learn":[0.3846747184],"iteration":239,"passed_time":0.20783271,"remaining_time":0}
]}